compas_ui/__init__.py
compas_ui/controller.py
compas_ui/scene.py
compas_ui/session.py
compas_ui/ui.py
compas_ui/artists/__init__.py
compas_ui/artists/curveartist.py
compas_ui/artists/meshartist.py
compas_ui/artists/primitiveartist.py
compas_ui/objects/__init__.py
compas_ui/objects/curveobject.py
compas_ui/objects/exceptions.py
compas_ui/objects/group.py
compas_ui/objects/groupobject.py
compas_ui/objects/lineobject.py
compas_ui/objects/meshobject.py
compas_ui/objects/networkobject.py
compas_ui/objects/object.py
compas_ui/objects/volmeshobject.py
compas_ui/rhino/__init__.py
compas_ui/rhino/callbacks.py
compas_ui/rhino/command.py
compas_ui/rhino/install.py
compas_ui/rhino/install_plugin.py
compas_ui/rhino/mouse.py
compas_ui/rhino/rui.py
compas_ui/rhino/scene.py
compas_ui/rhino/artists/__init__.py
compas_ui/rhino/artists/curveartist.py
compas_ui/rhino/artists/lineartist.py
compas_ui/rhino/artists/meshartist.py
compas_ui/rhino/forms/__init__.py
compas_ui/rhino/forms/about.py
compas_ui/rhino/forms/attributes.py
compas_ui/rhino/forms/conda.py
compas_ui/rhino/forms/defaultattributes.py
compas_ui/rhino/forms/error.py
compas_ui/rhino/forms/filesystem.py
compas_ui/rhino/forms/info.py
compas_ui/rhino/forms/meshdata.py
compas_ui/rhino/forms/scene.py
compas_ui/rhino/forms/searchpaths.py
compas_ui/rhino/forms/settings.py
compas_ui/rhino/forms/splash.py
compas_ui/rhino/forms/toolbar.py
compas_ui/rhino/objects/__init__.py
compas_ui/rhino/objects/_modify.py
compas_ui/rhino/objects/curveobject.py
compas_ui/rhino/objects/lineobject.py
compas_ui/rhino/objects/meshobject.py
compas_ui/rhino/objects/networkobject.py
compas_ui/rhino/objects/object.py
compas_ui/rhino/objects/volmeshobject.py
compas_ui/rhino/ui/COMPAS/dev/COMPAS__toolbar_cmd.py
compas_ui/rhino/ui/COMPAS/dev/COMPAS_cloud_restart_cmd.py
compas_ui/rhino/ui/COMPAS/dev/COMPAS_cloud_shutdown_cmd.py
compas_ui/rhino/ui/COMPAS/dev/COMPAS_cloud_start_cmd.py
compas_ui/rhino/ui/COMPAS/dev/COMPAS_conda_envs_cmd.py
compas_ui-0.9.3.dist-info/AUTHORS.md
compas_ui-0.9.3.dist-info/LICENSE
compas_ui-0.9.3.dist-info/METADATA
compas_ui-0.9.3.dist-info/WHEEL
compas_ui-0.9.3.dist-info/top_level.txt
compas_ui-0.9.3.dist-info/RECORD
