Metadata-Version: 2.1
Name: compas-ui
Version: 0.9.3
Summary: COMPAS UI provides basic functionality to build a user interface for a COMPAS app.
Home-page: https://github.com/blockresearchgroup/compas_ui
Author: tom van mele
Author-email: van.mele@arch.ethz.ch
License: MIT license
Classifier: Development Status :: 4 - Beta
Classifier: Intended Audience :: Developers
Classifier: Topic :: Scientific/Engineering
Classifier: License :: OSI Approved :: MIT License
Classifier: Operating System :: Unix
Classifier: Operating System :: POSIX
Classifier: Operating System :: Microsoft :: Windows
Classifier: Programming Language :: Python
Classifier: Programming Language :: Python :: 3
Classifier: Programming Language :: Python :: 3.8
Classifier: Programming Language :: Python :: 3.9
Classifier: Programming Language :: Python :: 3.10
Classifier: Programming Language :: Python :: Implementation :: CPython
Requires-Python: >=3.8
License-File: LICENSE
License-File: AUTHORS.md
Requires-Dist: compas
Requires-Dist: compas-cloud
